pyhaversion/__init__.py
pyhaversion/base.py
pyhaversion/consts.py
pyhaversion/container.py
pyhaversion/exceptions.py
pyhaversion/haio.py
pyhaversion/local.py
pyhaversion/pypi.py
pyhaversion/supervisor.py
pyhaversion/version.py
pyhaversion-24.6.1.dist-info/LICENSE
pyhaversion-24.6.1.dist-info/METADATA
pyhaversion-24.6.1.dist-info/WHEEL
pyhaversion-24.6.1.dist-info/RECORD
