Metadata-Version: 2.1
Name: pyhaversion
Version: 24.6.1
Summary: Get the latest Home Assistant version from various sources.
Home-page: https://github.com/ludeeus/pyhaversion
License: MIT
Keywords: homeassistant,version,update
Author: Joakim Sorensen
Author-email: hi@ludeeus.dev
Maintainer: Joakim Sorensen
Maintainer-email: hi@ludeeus.dev
Requires-Python: >=3.12,<4.0
Classifier: Intended Audience :: Developers
Classifier: License :: OSI Approved :: MIT License
Classifier: Natural Language :: English
Classifier: Programming Language :: Python :: 3
Classifier: Programming Language :: Python :: 3.12
Classifier: Topic :: Software Development :: Libraries :: Python Modules
Requires-Dist: aiohttp (>=3.6,<4.0)
Requires-Dist: awesomeversion (>21)
Project-URL: Repository, https://github.com/ludeeus/pyhaversion
